{
  "legislative_session": "2025",
  "identifier": "SB 566",
  "title": "Provide for the regulation of secure youth transportation companies",
  "from_organization": "~{\"classification\": \"upper\"}",
  "classification": [
    "bill"
  ],
  "subject": [
    "Health Care Services (see also: Health)",
    "Minors  (see also: Family Law)",
    "Revenue, State",
    "Safety  (see also: Health)",
    "State Government",
    "Transportation  (see also: Motor Vehicles; Taxation--Transportation)"
  ],
  "abstracts": [],
  "other_titles": [],
  "other_identifiers": [],
  "actions": [
    {
      "description": "(LC) Drafter Assigned",
      "date": "2024-11-11T21:17:46+00:00",
      "organization_id": "~{\"classification\": \"legislature\"}",
      "classification": [],
      "related_entities": [],
      "_processing": {
        "log_file_created": "2025-10-25T04:20:48Z"
      }
    },
    {
      "description": "(LC) Draft in Legal Review",
      "date": "2025-03-25T19:35:10+00:00",
      "organization_id": "~{\"classification\": \"legislature\"}",
      "classification": [],
      "related_entities": [],
      "_processing": {
        "log_file_created": "2025-10-25T04:20:48Z"
      }
    },
    {
      "description": "(LC) Draft in Edit",
      "date": "2025-03-25T20:17:28+00:00",
      "organization_id": "~{\"classification\": \"legislature\"}",
      "classification": [],
      "related_entities": [],
      "_processing": {
        "log_file_created": "2025-10-25T04:20:48Z"
      }
    },
    {
      "description": "(LC) Draft in Input/Proofing",
      "date": "2025-03-27T00:45:57+00:00",
      "organization_id": "~{\"classification\": \"legislature\"}",
      "classification": [],
      "related_entities": [],
      "_processing": {
        "log_file_created": "2025-10-25T04:20:48Z"
      }
    },
    {
      "description": "(LC) Draft in Final Drafter Review",
      "date": "2025-03-27T15:47:47+00:00",
      "organization_id": "~{\"classification\": \"legislature\"}",
      "classification": [],
      "related_entities": [],
      "_processing": {
        "log_file_created": "2025-10-25T04:20:48Z"
      }
    },
    {
      "description": "(LC) Draft in Assembly",
      "date": "2025-03-27T17:23:04+00:00",
      "organization_id": "~{\"classification\": \"legislature\"}",
      "classification": [],
      "related_entities": [],
      "_processing": {
        "log_file_created": "2025-10-25T04:20:48Z"
      }
    },
    {
      "description": "(LC) Draft Delivered to Requester",
      "date": "2025-03-28T21:41:52+00:00",
      "organization_id": "~{\"classification\": \"legislature\"}",
      "classification": [],
      "related_entities": [],
      "_processing": {
        "log_file_created": "2025-10-25T04:20:48Z"
      }
    },
    {
      "description": "(S) Introduced",
      "date": "2025-03-31T22:14:26+00:00",
      "organization_id": "~{\"classification\": \"upper\"}",
      "classification": [],
      "related_entities": [],
      "_processing": {
        "log_file_created": "2025-10-25T04:20:48Z"
      }
    },
    {
      "description": "(S) Fiscal Note Requested",
      "date": "2025-04-01T16:22:08+00:00",
      "organization_id": "~{\"classification\": \"upper\"}",
      "classification": [],
      "related_entities": [],
      "_processing": {
        "log_file_created": "2025-10-25T04:20:48Z"
      }
    },
    {
      "description": "(S) First Reading",
      "date": "2025-04-01T19:10:26+00:00",
      "organization_id": "~{\"classification\": \"upper\"}",
      "classification": [
        "reading-1"
      ],
      "related_entities": [],
      "_processing": {
        "log_file_created": "2025-10-25T04:20:48Z"
      }
    },
    {
      "description": "(S) Referred to Committee - (S) Public Health, Welfare and Safety",
      "date": "2025-04-01T19:11:00+00:00",
      "organization_id": "~{\"classification\": \"upper\"}",
      "classification": [
        "referral-committee"
      ],
      "related_entities": [],
      "_processing": {
        "log_file_created": "2025-10-25T04:20:48Z"
      }
    },
    {
      "description": "(S) Hearing - (S) Public Health, Welfare and Safety",
      "date": "2025-04-02T17:36:24+00:00",
      "organization_id": "~{\"classification\": \"upper\"}",
      "classification": [],
      "related_entities": [],
      "_processing": {
        "log_file_created": "2025-10-25T04:20:48Z"
      }
    },
    {
      "description": "(S) Tabled in Committee - (S) Public Health, Welfare and Safety",
      "date": "2025-04-03T02:40:45+00:00",
      "organization_id": "~{\"classification\": \"upper\"}",
      "classification": [
        "amendment-deferral"
      ],
      "related_entities": [],
      "_processing": {
        "log_file_created": "2025-10-25T04:20:48Z"
      }
    },
    {
      "description": "(S) Fiscal Note Received",
      "date": "2025-04-04T21:57:33+00:00",
      "organization_id": "~{\"classification\": \"upper\"}",
      "classification": [
        "receipt"
      ],
      "related_entities": [],
      "_processing": {
        "log_file_created": "2025-10-25T04:20:48Z"
      }
    },
    {
      "description": "(S) Fiscal Note Unsigned",
      "date": "2025-04-04T21:57:41+00:00",
      "organization_id": "~{\"classification\": \"upper\"}",
      "classification": [],
      "related_entities": [],
      "_processing": {
        "log_file_created": "2025-10-25T04:20:48Z"
      }
    },
    {
      "description": "(S) Fiscal Note Printed",
      "date": "2025-04-05T01:56:32+00:00",
      "organization_id": "~{\"classification\": \"upper\"}",
      "classification": [],
      "related_entities": [],
      "_processing": {
        "log_file_created": "2025-10-25T04:20:48Z"
      }
    },
    {
      "description": "(S) Missed Deadline for Revenue Bill Transmittal",
      "date": "2025-04-07T17:00:35+00:00",
      "organization_id": "~{\"classification\": \"upper\"}",
      "classification": [],
      "related_entities": [],
      "_processing": {
        "log_file_created": "2025-10-25T04:20:48Z"
      }
    },
    {
      "description": "(S) Died in Process",
      "date": "2025-05-23T19:47:05+00:00",
      "organization_id": "~{\"classification\": \"upper\"}",
      "classification": [
        "failure"
      ],
      "related_entities": [],
      "_processing": {
        "log_file_created": "2025-10-25T04:20:48Z"
      }
    }
  ],
  "sponsorships": [
    {
      "name": "Laura Smith",
      "classification": "primary",
      "entity_type": "person",
      "primary": true,
      "person_id": "~{\"name\": \"Laura Smith\"}",
      "organization_id": null
    }
  ],
  "related_bills": [
    {
      "identifier": "LC 1093",
      "legislative_session": "2025",
      "relation_type": "replaces"
    }
  ],
  "versions": [
    {
      "note": "SB0566_1(1).pdf",
      "links": [
        {
          "url": "https://api.legmt.gov/docs/v1/documents/getContent?documentId=302186",
          "media_type": "application/pdf"
        }
      ],
      "date": "",
      "classification": ""
    },
    {
      "note": "SB0566_1(2).pdf",
      "links": [
        {
          "url": "https://api.legmt.gov/docs/v1/documents/getContent?documentId=323942",
          "media_type": "application/pdf"
        }
      ],
      "date": "",
      "classification": ""
    },
    {
      "note": "SB0566_1(3).pdf",
      "links": [
        {
          "url": "https://api.legmt.gov/docs/v1/documents/getContent?documentId=326089",
          "media_type": "application/pdf"
        }
      ],
      "date": "",
      "classification": ""
    },
    {
      "note": "SB0566_1.pdf",
      "links": [
        {
          "url": "https://api.legmt.gov/docs/v1/documents/getContent?documentId=301856",
          "media_type": "application/pdf"
        }
      ],
      "date": "",
      "classification": ""
    },
    {
      "note": "LC1093.pdf",
      "links": [
        {
          "url": "https://api.legmt.gov/docs/v1/documents/getContent?documentId=299218",
          "media_type": "application/pdf"
        }
      ],
      "date": "",
      "classification": ""
    }
  ],
  "documents": [
    {
      "note": "Fiscal Note: SB0566_1.pdf",
      "links": [
        {
          "url": "https://api.legmt.gov/docs/v1/documents/getContent?documentId=304968",
          "media_type": "application/pdf"
        }
      ],
      "date": "",
      "classification": ""
    }
  ],
  "citations": [],
  "sources": [
    {
      "url": "https://bills.legmt.gov/#/laws/bill/2/LC1093?open_tab=sum",
      "note": ""
    }
  ],
  "extras": {
    "bill_draft_number": "LC1093",
    "by_request_of": "Laura Smith"
  },
  "jurisdiction": {
    "id": "ocd-jurisdiction/country:us/state:mt/government",
    "name": "Montana",
    "classification": "state",
    "division_id": "ocd-division/country:us/state:mt"
  },
  "_processing": {
    "logs_latest_update": "2025-10-25T04:20:48Z"
  }
}