{
  "legislative_session": "2025",
  "identifier": "HB 552",
  "title": "Revise worker's compensation law to cover PTSD for first responders and others",
  "from_organization": "~{\"classification\": \"lower\"}",
  "classification": [
    "bill"
  ],
  "subject": [
    "Workers' Compensation  (see also: Labor and Employment)"
  ],
  "abstracts": [],
  "other_titles": [],
  "other_identifiers": [],
  "actions": [
    {
      "description": "(LC) Drafter Assigned",
      "date": "2024-11-16T23:36:30+00:00",
      "organization_id": "~{\"classification\": \"legislature\"}",
      "classification": [],
      "related_entities": [],
      "_processing": {
        "log_file_created": "2025-10-25T04:20:55Z"
      }
    },
    {
      "description": "(LC) Draft in Legal Review",
      "date": "2024-12-31T20:21:10+00:00",
      "organization_id": "~{\"classification\": \"legislature\"}",
      "classification": [],
      "related_entities": [],
      "_processing": {
        "log_file_created": "2025-10-25T04:20:55Z"
      }
    },
    {
      "description": "(LC) Draft in Edit",
      "date": "2025-01-06T23:26:06+00:00",
      "organization_id": "~{\"classification\": \"legislature\"}",
      "classification": [],
      "related_entities": [],
      "_processing": {
        "log_file_created": "2025-10-25T04:20:55Z"
      }
    },
    {
      "description": "(LC) Draft in Input/Proofing",
      "date": "2025-01-10T22:11:22+00:00",
      "organization_id": "~{\"classification\": \"legislature\"}",
      "classification": [],
      "related_entities": [],
      "_processing": {
        "log_file_created": "2025-10-25T04:20:55Z"
      }
    },
    {
      "description": "(LC) Draft in Final Drafter Review",
      "date": "2025-01-13T17:16:30+00:00",
      "organization_id": "~{\"classification\": \"legislature\"}",
      "classification": [],
      "related_entities": [],
      "_processing": {
        "log_file_created": "2025-10-25T04:20:55Z"
      }
    },
    {
      "description": "(LC) Draft in Assembly",
      "date": "2025-01-14T13:40:00+00:00",
      "organization_id": "~{\"classification\": \"legislature\"}",
      "classification": [],
      "related_entities": [],
      "_processing": {
        "log_file_created": "2025-10-25T04:20:55Z"
      }
    },
    {
      "description": "(LC) Draft Ready for Delivery",
      "date": "2025-01-14T16:20:27+00:00",
      "organization_id": "~{\"classification\": \"legislature\"}",
      "classification": [],
      "related_entities": [],
      "_processing": {
        "log_file_created": "2025-10-25T04:20:55Z"
      }
    },
    {
      "description": "(LC) Drafter Assigned",
      "date": "2025-02-03T18:53:29+00:00",
      "organization_id": "~{\"classification\": \"legislature\"}",
      "classification": [],
      "related_entities": [],
      "_processing": {
        "log_file_created": "2025-10-25T04:20:55Z"
      }
    },
    {
      "description": "(LC) Draft in Legal Review",
      "date": "2025-02-10T15:43:23+00:00",
      "organization_id": "~{\"classification\": \"legislature\"}",
      "classification": [],
      "related_entities": [],
      "_processing": {
        "log_file_created": "2025-10-25T04:20:55Z"
      }
    },
    {
      "description": "(LC) Draft in Edit",
      "date": "2025-02-10T23:56:53+00:00",
      "organization_id": "~{\"classification\": \"legislature\"}",
      "classification": [],
      "related_entities": [],
      "_processing": {
        "log_file_created": "2025-10-25T04:20:55Z"
      }
    },
    {
      "description": "(LC) Draft in Input/Proofing",
      "date": "2025-02-13T13:49:05+00:00",
      "organization_id": "~{\"classification\": \"legislature\"}",
      "classification": [],
      "related_entities": [],
      "_processing": {
        "log_file_created": "2025-10-25T04:20:55Z"
      }
    },
    {
      "description": "(LC) Draft in Final Drafter Review",
      "date": "2025-02-14T16:31:21+00:00",
      "organization_id": "~{\"classification\": \"legislature\"}",
      "classification": [],
      "related_entities": [],
      "_processing": {
        "log_file_created": "2025-10-25T04:20:55Z"
      }
    },
    {
      "description": "(LC) Draft in Assembly",
      "date": "2025-02-14T21:21:18+00:00",
      "organization_id": "~{\"classification\": \"legislature\"}",
      "classification": [],
      "related_entities": [],
      "_processing": {
        "log_file_created": "2025-10-25T04:20:55Z"
      }
    },
    {
      "description": "(LC) Draft Ready for Delivery",
      "date": "2025-02-17T14:25:43+00:00",
      "organization_id": "~{\"classification\": \"legislature\"}",
      "classification": [],
      "related_entities": [],
      "_processing": {
        "log_file_created": "2025-10-25T04:20:55Z"
      }
    },
    {
      "description": "(LC) Draft Delivered to Requester",
      "date": "2025-02-18T15:42:41+00:00",
      "organization_id": "~{\"classification\": \"legislature\"}",
      "classification": [],
      "related_entities": [],
      "_processing": {
        "log_file_created": "2025-10-25T04:20:55Z"
      }
    },
    {
      "description": "(H) Introduced",
      "date": "2025-02-18T22:12:56+00:00",
      "organization_id": "~{\"classification\": \"lower\"}",
      "classification": [],
      "related_entities": [],
      "_processing": {
        "log_file_created": "2025-10-25T04:20:55Z"
      }
    },
    {
      "description": "(H) Fiscal Note Requested",
      "date": "2025-02-18T22:48:22+00:00",
      "organization_id": "~{\"classification\": \"lower\"}",
      "classification": [],
      "related_entities": [],
      "_processing": {
        "log_file_created": "2025-10-25T04:20:55Z"
      }
    },
    {
      "description": "(H) Referred to Committee - (H) Business and Labor",
      "date": "2025-02-19T19:32:04+00:00",
      "organization_id": "~{\"classification\": \"lower\"}",
      "classification": [
        "referral-committee"
      ],
      "related_entities": [],
      "_processing": {
        "log_file_created": "2025-10-25T04:20:55Z"
      }
    },
    {
      "description": "(H) First Reading",
      "date": "2025-02-19T19:52:09+00:00",
      "organization_id": "~{\"classification\": \"lower\"}",
      "classification": [
        "reading-1"
      ],
      "related_entities": [],
      "_processing": {
        "log_file_created": "2025-10-25T04:20:55Z"
      }
    },
    {
      "description": "(H) Hearing - (H) Business and Labor",
      "date": "2025-02-21T15:15:48+00:00",
      "organization_id": "~{\"classification\": \"lower\"}",
      "classification": [],
      "related_entities": [],
      "_processing": {
        "log_file_created": "2025-10-25T04:20:55Z"
      }
    },
    {
      "description": "(H) Hearing - (H) Business and Labor",
      "date": "2025-02-24T14:33:17+00:00",
      "organization_id": "~{\"classification\": \"lower\"}",
      "classification": [],
      "related_entities": [],
      "_processing": {
        "log_file_created": "2025-10-25T04:20:55Z"
      }
    },
    {
      "description": "(H) Fiscal Note Received",
      "date": "2025-02-25T13:27:01+00:00",
      "organization_id": "~{\"classification\": \"lower\"}",
      "classification": [
        "receipt"
      ],
      "related_entities": [],
      "_processing": {
        "log_file_created": "2025-10-25T04:20:55Z"
      }
    },
    {
      "description": "(H) Fiscal Note Unsigned",
      "date": "2025-02-27T00:56:56+00:00",
      "organization_id": "~{\"classification\": \"lower\"}",
      "classification": [],
      "related_entities": [],
      "_processing": {
        "log_file_created": "2025-10-25T04:20:55Z"
      }
    },
    {
      "description": "(H) Sponsor Rebuttal to Fiscal Note Requested",
      "date": "2025-02-27T01:00:00+00:00",
      "organization_id": "~{\"classification\": \"lower\"}",
      "classification": [],
      "related_entities": [],
      "_processing": {
        "log_file_created": "2025-10-25T04:20:55Z"
      }
    },
    {
      "description": "(H) Fiscal Note Printed",
      "date": "2025-02-27T16:27:00+00:00",
      "organization_id": "~{\"classification\": \"lower\"}",
      "classification": [],
      "related_entities": [],
      "_processing": {
        "log_file_created": "2025-10-25T04:20:55Z"
      }
    },
    {
      "description": "(H) Committee Executive Action--Bill Passed as Amended - (H) Business and Labor",
      "date": "2025-02-28T17:37:59+00:00",
      "organization_id": "~{\"classification\": \"lower\"}",
      "classification": [
        "committee-passage"
      ],
      "related_entities": [],
      "_processing": {
        "log_file_created": "2025-10-25T04:20:55Z"
      }
    },
    {
      "description": "(H) Sponsor Rebuttal to Fiscal Note Received",
      "date": "2025-02-28T19:23:49+00:00",
      "organization_id": "~{\"classification\": \"lower\"}",
      "classification": [
        "receipt"
      ],
      "related_entities": [],
      "_processing": {
        "log_file_created": "2025-10-25T04:20:55Z"
      }
    },
    {
      "description": "(H) Sponsor Rebuttal to Fiscal Note Signed",
      "date": "2025-02-28T19:23:55+00:00",
      "organization_id": "~{\"classification\": \"lower\"}",
      "classification": [],
      "related_entities": [],
      "_processing": {
        "log_file_created": "2025-10-25T04:20:55Z"
      }
    },
    {
      "description": "(H) Committee Report--Bill Passed as Amended - (H) Business and Labor",
      "date": "2025-02-28T21:12:20+00:00",
      "organization_id": "~{\"classification\": \"lower\"}",
      "classification": [
        "committee-passage"
      ],
      "related_entities": [],
      "_processing": {
        "log_file_created": "2025-10-25T04:20:55Z"
      }
    },
    {
      "description": "(H) Revised Fiscal Note Requested",
      "date": "2025-03-01T18:41:29+00:00",
      "organization_id": "~{\"classification\": \"lower\"}",
      "classification": [],
      "related_entities": [],
      "_processing": {
        "log_file_created": "2025-10-25T04:20:55Z"
      }
    },
    {
      "description": "(H) Scheduled for 2nd Reading",
      "date": "2025-03-03T20:00:00+00:00",
      "organization_id": "~{\"classification\": \"lower\"}",
      "classification": [
        "reading-2"
      ],
      "related_entities": [],
      "_processing": {
        "log_file_created": "2025-10-25T04:20:55Z"
      }
    },
    {
      "description": "(H) 2nd Reading Passed",
      "date": "2025-03-03T20:59:00+00:00",
      "organization_id": "~{\"classification\": \"lower\"}",
      "classification": [
        "reading-2",
        "reading-2"
      ],
      "related_entities": [],
      "_processing": {
        "log_file_created": "2025-10-25T04:20:55Z"
      }
    },
    {
      "description": "(H) Rereferred to Committee - (H) Appropriations",
      "date": "2025-03-03T21:54:00+00:00",
      "organization_id": "~{\"classification\": \"lower\"}",
      "classification": [
        "referral-committee",
        "referral-committee"
      ],
      "related_entities": [],
      "_processing": {
        "log_file_created": "2025-10-25T04:20:55Z"
      }
    },
    {
      "description": "(H) Hearing - (H) Appropriations",
      "date": "2025-03-03T22:28:43+00:00",
      "organization_id": "~{\"classification\": \"lower\"}",
      "classification": [],
      "related_entities": [],
      "_processing": {
        "log_file_created": "2025-10-25T04:20:55Z"
      }
    },
    {
      "description": "(H) Tabled in Committee - (H) Appropriations",
      "date": "2025-03-03T23:03:11+00:00",
      "organization_id": "~{\"classification\": \"lower\"}",
      "classification": [
        "amendment-deferral"
      ],
      "related_entities": [],
      "_processing": {
        "log_file_created": "2025-10-25T04:20:55Z"
      }
    },
    {
      "description": "(H) Motion Failed",
      "date": "2025-03-04T01:46:00+00:00",
      "organization_id": "~{\"classification\": \"lower\"}",
      "classification": [
        "failure"
      ],
      "related_entities": [],
      "_processing": {
        "log_file_created": "2025-10-25T04:20:55Z"
      }
    },
    {
      "description": "(H) Revised Fiscal Note Received",
      "date": "2025-03-04T20:42:00+00:00",
      "organization_id": "~{\"classification\": \"lower\"}",
      "classification": [
        "receipt"
      ],
      "related_entities": [],
      "_processing": {
        "log_file_created": "2025-10-25T04:20:55Z"
      }
    },
    {
      "description": "(H) Missed Deadline for General Bill Transmittal",
      "date": "2025-03-12T19:00:00+00:00",
      "organization_id": "~{\"classification\": \"lower\"}",
      "classification": [],
      "related_entities": [],
      "_processing": {
        "log_file_created": "2025-10-25T04:20:55Z"
      }
    },
    {
      "description": "(H) Died in Process",
      "date": "2025-05-20T17:00:00+00:00",
      "organization_id": "~{\"classification\": \"lower\"}",
      "classification": [
        "failure"
      ],
      "related_entities": [],
      "_processing": {
        "log_file_created": "2025-10-25T04:20:55Z"
      }
    }
  ],
  "sponsorships": [
    {
      "name": "James Reavis",
      "classification": "primary",
      "entity_type": "person",
      "primary": true,
      "person_id": "~{\"name\": \"James Reavis\"}",
      "organization_id": null
    }
  ],
  "related_bills": [
    {
      "identifier": "LC 1564",
      "legislative_session": "2025",
      "relation_type": "replaces"
    }
  ],
  "versions": [
    {
      "note": "HB0552_1(1).pdf",
      "links": [
        {
          "url": "https://api.legmt.gov/docs/v1/documents/getContent?documentId=284417",
          "media_type": "application/pdf"
        }
      ],
      "date": "",
      "classification": ""
    },
    {
      "note": "HB0552_1(2).pdf",
      "links": [
        {
          "url": "https://api.legmt.gov/docs/v1/documents/getContent?documentId=290082",
          "media_type": "application/pdf"
        }
      ],
      "date": "",
      "classification": ""
    },
    {
      "note": "HB0552_1(3).pdf",
      "links": [
        {
          "url": "https://api.legmt.gov/docs/v1/documents/getContent?documentId=290083",
          "media_type": "application/pdf"
        }
      ],
      "date": "",
      "classification": ""
    },
    {
      "note": "HB0552_1(4).pdf",
      "links": [
        {
          "url": "https://api.legmt.gov/docs/v1/documents/getContent?documentId=290084",
          "media_type": "application/pdf"
        }
      ],
      "date": "",
      "classification": ""
    },
    {
      "note": "HB0552_1(5).pdf",
      "links": [
        {
          "url": "https://api.legmt.gov/docs/v1/documents/getContent?documentId=290085",
          "media_type": "application/pdf"
        }
      ],
      "date": "",
      "classification": ""
    },
    {
      "note": "HB0552_1.pdf",
      "links": [
        {
          "url": "https://api.legmt.gov/docs/v1/documents/getContent?documentId=283854",
          "media_type": "application/pdf"
        }
      ],
      "date": "",
      "classification": ""
    },
    {
      "note": "HB0552_2(1).pdf",
      "links": [
        {
          "url": "https://api.legmt.gov/docs/v1/documents/getContent?documentId=290087",
          "media_type": "application/pdf"
        }
      ],
      "date": "",
      "classification": ""
    },
    {
      "note": "HB0552_2(2).pdf",
      "links": [
        {
          "url": "https://api.legmt.gov/docs/v1/documents/getContent?documentId=290088",
          "media_type": "application/pdf"
        }
      ],
      "date": "",
      "classification": ""
    },
    {
      "note": "HB0552_2(3).pdf",
      "links": [
        {
          "url": "https://api.legmt.gov/docs/v1/documents/getContent?documentId=290136",
          "media_type": "application/pdf"
        }
      ],
      "date": "",
      "classification": ""
    },
    {
      "note": "HB0552_2(4).pdf",
      "links": [
        {
          "url": "https://api.legmt.gov/docs/v1/documents/getContent?documentId=290138",
          "media_type": "application/pdf"
        }
      ],
      "date": "",
      "classification": ""
    },
    {
      "note": "HB0552_2(5).pdf",
      "links": [
        {
          "url": "https://api.legmt.gov/docs/v1/documents/getContent?documentId=290141",
          "media_type": "application/pdf"
        }
      ],
      "date": "",
      "classification": ""
    },
    {
      "note": "HB0552_2(6).pdf",
      "links": [
        {
          "url": "https://api.legmt.gov/docs/v1/documents/getContent?documentId=290152",
          "media_type": "application/pdf"
        }
      ],
      "date": "",
      "classification": ""
    },
    {
      "note": "HB0552_2(7).pdf",
      "links": [
        {
          "url": "https://api.legmt.gov/docs/v1/documents/getContent?documentId=323773",
          "media_type": "application/pdf"
        }
      ],
      "date": "",
      "classification": ""
    },
    {
      "note": "HB0552_2(8).pdf",
      "links": [
        {
          "url": "https://api.legmt.gov/docs/v1/documents/getContent?documentId=326259",
          "media_type": "application/pdf"
        }
      ],
      "date": "",
      "classification": ""
    },
    {
      "note": "HB0552_2(9).pdf",
      "links": [
        {
          "url": "https://api.legmt.gov/docs/v1/documents/getContent?documentId=327550",
          "media_type": "application/pdf"
        }
      ],
      "date": "",
      "classification": ""
    },
    {
      "note": "HB0552_2.pdf",
      "links": [
        {
          "url": "https://api.legmt.gov/docs/v1/documents/getContent?documentId=290086",
          "media_type": "application/pdf"
        }
      ],
      "date": "",
      "classification": ""
    },
    {
      "note": "HB0552.001.001_Amendments-in-Context_final-full.pdf",
      "links": [
        {
          "url": "https://api.legmt.gov/docs/v1/documents/getContent?documentId=289063",
          "media_type": "application/pdf"
        }
      ],
      "date": "",
      "classification": ""
    },
    {
      "note": "HB0552.001.002_Amendments-in-Context_final-full.pdf",
      "links": [
        {
          "url": "https://api.legmt.gov/docs/v1/documents/getContent?documentId=289592",
          "media_type": "application/pdf"
        }
      ],
      "date": "",
      "classification": ""
    },
    {
      "note": "LC1564.pdf",
      "links": [
        {
          "url": "https://api.legmt.gov/docs/v1/documents/getContent?documentId=270882",
          "media_type": "application/pdf"
        }
      ],
      "date": "",
      "classification": ""
    }
  ],
  "documents": [
    {
      "note": "Fiscal Note: HB0552_1.pdf",
      "links": [
        {
          "url": "https://api.legmt.gov/docs/v1/documents/getContent?documentId=288954",
          "media_type": "application/pdf"
        }
      ],
      "date": "",
      "classification": ""
    },
    {
      "note": "Fiscal Note: HB0552_2.pdf",
      "links": [
        {
          "url": "https://api.legmt.gov/docs/v1/documents/getContent?documentId=294373",
          "media_type": "application/pdf"
        }
      ],
      "date": "",
      "classification": ""
    }
  ],
  "citations": [],
  "sources": [
    {
      "url": "https://bills.legmt.gov/#/laws/bill/2/LC1564?open_tab=sum",
      "note": ""
    }
  ],
  "extras": {
    "bill_draft_number": "LC1564",
    "by_request_of": "James Reavis"
  },
  "jurisdiction": {
    "id": "ocd-jurisdiction/country:us/state:mt/government",
    "name": "Montana",
    "classification": "state",
    "division_id": "ocd-division/country:us/state:mt"
  },
  "_processing": {
    "logs_latest_update": "2025-10-25T04:20:55Z",
    "text_extraction_latest_update": "2025-10-27T10:41:31.266171Z"
  }
}