{
  "identifier": "2025-HB 387-4705",
  "motion_text": "be_concurred_in",
  "motion_classification": [],
  "start_date": "2025-03-26T21:23:53+00:00",
  "result": "pass",
  "organization": "~{\"classification\": \"upper\"}",
  "legislative_session": "2025",
  "bill": "62042f3c-b153-11f0-b804-86bb9c4cb8d3",
  "bill_action": "(S) Committee Executive Action--Bill Concurred",
  "bill_identifier": "HB 387",
  "votes": [
    {
      "option": "yes",
      "voter_name": "John Esp",
      "voter_id": "~{\"name\": \"John Esp\"}",
      "note": ""
    },
    {
      "option": "yes",
      "voter_name": "Dave Fern",
      "voter_id": "~{\"name\": \"Dave Fern\"}",
      "note": ""
    },
    {
      "option": "yes",
      "voter_name": "Sen Elect Gregg Hunter",
      "voter_id": "~{\"name\": \"Sen Elect Gregg Hunter\"}",
      "note": ""
    },
    {
      "option": "yes",
      "voter_name": "Josh Kassmier",
      "voter_id": "~{\"name\": \"Josh Kassmier\"}",
      "note": ""
    },
    {
      "option": "yes",
      "voter_name": "Andrea Olsen",
      "voter_id": "~{\"name\": \"Andrea Olsen\"}",
      "note": ""
    },
    {
      "option": "yes",
      "voter_name": "Mary Ann Dunwell",
      "voter_id": "~{\"name\": \"Mary Ann Dunwell\"}",
      "note": ""
    },
    {
      "option": "yes",
      "voter_name": "Denley Loge",
      "voter_id": "~{\"name\": \"Denley Loge\"}",
      "note": ""
    },
    {
      "option": "yes",
      "voter_name": "Russ Tempel",
      "voter_id": "~{\"name\": \"Russ Tempel\"}",
      "note": ""
    }
  ],
  "counts": [
    {
      "option": "yes",
      "value": 8
    },
    {
      "option": "no",
      "value": 0
    },
    {
      "option": "absent",
      "value": 0
    },
    {
      "option": "excused",
      "value": 0
    },
    {
      "option": "abstain",
      "value": 0
    }
  ],
  "sources": [
    {
      "url": "https://bills.legmt.gov/#/laws/bill/2/LC1517?open_tab=sum",
      "note": ""
    }
  ],
  "extras": {}
}